__init__.py
shifiq.py
api/__init__.py
api/connection.py
api/player/__init__.py
api/player/player.py
client/__init__.py
client/client.py
shifiq_api_client-0.1.0.dist-info/LICENSE
shifiq_api_client-0.1.0.dist-info/METADATA
shifiq_api_client-0.1.0.dist-info/WHEEL
shifiq_api_client-0.1.0.dist-info/top_level.txt
shifiq_api_client-0.1.0.dist-info/RECORD
